LICENSE
querius/__init__.py
querius/client.py
querius/patch.py
querius/secretmanager.py
querius-0.1.10.dist-info/LICENSE
querius-0.1.10.dist-info/WHEEL
querius-0.1.10.dist-info/METADATA
querius-0.1.10.dist-info/RECORD
