Metadata-Version: 2.1
Name: querius
Version: 0.1.10
Summary: Client library for connecting with the Querius API
Home-page: https://getquerius.com
License: Apache-2.0
Keywords: querius,bigquery,query,optimisation,api
Author: Theo Windebank
Author-email: theo@getquerius.com
Requires-Python: >3.7,<3.10
Classifier: License :: OSI Approved :: Apache Software License
Classifier: Programming Language :: Python :: 3
Classifier: Programming Language :: Python :: 3.8
Classifier: Programming Language :: Python :: 3.9
Provides-Extra: google-cloud-secret-manager
Requires-Dist: google-auth (>=1.5,<2.0)
Requires-Dist: google-cloud-bigquery (>=1.5.0,<=2)
Requires-Dist: google-cloud-secret-manager (>=2.0.0,<3.0.0); extra == "google-cloud-secret-manager"
Requires-Dist: loguru (>=0.5,<0.6)
Requires-Dist: timeout-decorator (>=0.5.0,<0.6.0)
Project-URL: Repository, https://github.com/querius-dev/client
